table_extractor/__init__.py
table_extractor/context_extractor.py
table_extractor/exceptions.py
table_extractor/fetch_table.py
table_extractor/models/__init__.py
table_extractor/models/context.py
table_extractor/models/html_table.py
table_extractor/table_extractor.py
web_table_extractor-1.3.0.dist-info/WHEEL
web_table_extractor-1.3.0.dist-info/METADATA
web_table_extractor-1.3.0.dist-info/RECORD
