Metadata-Version: 2.1
Name: web-table-extractor
Version: 1.3.0
Summary: Extract tables from HTML
License: MIT
Author: Binh Vu
Author-email: binh@toan2.com
Requires-Python: >=3.8,<4.0
Classifier: License :: OSI Approved :: MIT License
Classifier: Programming Language :: Python :: 3
Classifier: Programming Language :: Python :: 3.10
Classifier: Programming Language :: Python :: 3.8
Classifier: Programming Language :: Python :: 3.9
Requires-Dist: beautifulsoup4 (>=4.9.3,<5.0.0)
Requires-Dist: html5lib (>=1.1,<2.0)
Requires-Dist: requests (>=2.28.0,<3.0.0)
